eca/__init__.py
eca/boolean_cube.py
eca/elementary_cellular_automtata.py
eca-0.0.12.dist-info/METADATA
eca-0.0.12.dist-info/WHEEL
eca-0.0.12.dist-info/top_level.txt
eca-0.0.12.dist-info/RECORD
