Metadata-Version: 2.1
Name: eca
Version: 0.0.12
Summary: One Dimensional Elementary Cellular Automata
Home-page: UNKNOWN
Author: Mohammed Terry-Jack
Author-email: <mohammedteryjack@gmail.com>
License: UNKNOWN
Keywords: python,cellular automata,elementary cellular automata,ca,one dimensional,1D
Platform: UNKNOWN
Requires-Dist: numpy
